{
    "pools": [
      {
        "rolls": 1,
        "entries": [
          {
            "type": "minecraft:item",
            "name": "spartanweaponry:quarterstaff_iron",
            "weight": 1
          },
          {
            "type": "minecraft:item",
            "name": "spartanweaponry:glaive_iron",
            "weight": 1
          },
          {
            "type": "minecraft:item",
            "name": "spartanweaponry:flanged_mace_iron",
            "weight": 1
          },
          {
            "type": "minecraft:item",
            "name": "spartanweaponry:battleaxe_iron",
            "weight": 1
          },
          {
            "type": "minecraft:item",
            "name": "spartanweaponry:heavy_crossbow_iron",
            "weight": 1
          },
          {
            "type": "minecraft:item",
            "name": "spartanweaponry:longbow_iron",
            "weight": 1
          },
          {
            "type": "minecraft:item",
            "name": "spartanweaponry:lance_iron",
            "weight": 1
          },
          {
            "type": "minecraft:item",
            "name": "spartanweaponry:pike_iron",
            "weight": 1
          },
          {
            "type": "minecraft:item",
            "name": "spartanweaponry:halberd_iron",
            "weight": 1
          },
          {
            "type": "minecraft:item",
            "name": "spartanweaponry:spear_iron",
            "weight": 1
          },
          {
            "type": "minecraft:item",
            "name": "spartanweaponry:warhammer_iron",
            "weight": 1
          },
          {
            "type": "minecraft:item",
            "name": "spartanweaponry:hammer_iron",
            "weight": 1
          },
          {
            "type": "minecraft:item",
            "name": "spartanweaponry:greatsword_iron",
            "weight": 1
          },
          {
            "type": "minecraft:item",
            "name": "spartanweaponry:rapier_iron",
            "weight": 1
          },
          {
            "type": "minecraft:item",
            "name": "spartanweaponry:saber_iron",
            "weight": 1
          },
          {
            "type": "minecraft:item",
            "name": "spartanweaponry:katana_iron",
            "weight": 1
          },
          {
            "type": "minecraft:item",
            "name": "spartanweaponry:longsword_iron",
            "weight": 1
          },
          {
            "type": "minecraft:item",
            "name": "spartanweaponry:dagger_iron",
            "weight": 1
          }
        ]
      }
    ]
  }